LICENSE
notifiers/__init__.py
notifiers/_version.py
notifiers/core.py
notifiers/exceptions.py
notifiers/logging.py
notifiers/providers/__init__.py
notifiers/providers/email.py
notifiers/providers/gitter.py
notifiers/providers/gmail.py
notifiers/providers/icloud.py
notifiers/providers/join.py
notifiers/providers/mailgun.py
notifiers/providers/pagerduty.py
notifiers/providers/popcornnotify.py
notifiers/providers/pushbullet.py
notifiers/providers/pushover.py
notifiers/providers/simplepush.py
notifiers/providers/slack.py
notifiers/providers/statuspage.py
notifiers/providers/telegram.py
notifiers/providers/twilio.py
notifiers/providers/victorops.py
notifiers/providers/zulip.py
notifiers/utils/__init__.py
notifiers/utils/helpers.py
notifiers/utils/requests.py
notifiers/utils/schema/__init__.py
notifiers/utils/schema/formats.py
notifiers/utils/schema/helpers.py
notifiers_cli/__init__.py
notifiers_cli/core.py
notifiers_cli/utils/__init__.py
notifiers_cli/utils/callbacks.py
notifiers_cli/utils/dynamic_click.py
notifiers-1.3.4.dist-info/METADATA
notifiers-1.3.4.dist-info/WHEEL
notifiers-1.3.4.dist-info/entry_points.txt
notifiers-1.3.4.dist-info/licenses/LICENSE
notifiers-1.3.4.dist-info/RECORD
