Metadata-Version: 2.4
Name: notifiers
Version: 1.3.4
Summary: The easy way to send notifications
Project-URL: Homepage, https://github.com/liiight/notifiers
Project-URL: Repository, https://github.com/liiight/notifiers
Project-URL: Documentation, https://notifiers.readthedocs.io/en/latest/
Author-email: liiight <or.carmi82@gmail.com>
License-Expression: MIT
License-File: LICENSE
Keywords: email,messaging,notifications,push
Classifier: Development Status :: 5 - Production/Stable
Classifier: Intended Audience :: Developers
Classifier: Intended Audience :: End Users/Desktop
Classifier: License :: OSI Approved :: MIT License
Classifier: Operating System :: OS Independent
Classifier: Programming Language :: Python
Classifier: Programming Language :: Python :: 3.7
Classifier: Programming Language :: Python :: 3.8
Classifier: Programming Language :: Python :: 3.9
Classifier: Programming Language :: Python :: 3.10
Requires-Python: ~=3.7
Requires-Dist: click<9,>=8.0.3
Requires-Dist: jsonschema<5,>=4.4.0
Requires-Dist: requests<3,>=2.27.1
